ISSUES
LICENSE
MANIFEST.in
README.md
run_tests.sh
setup.py
sudo_apt-get_install.sh
sudo_pip_install.sh
demos/lx_html5lib.py
demos/lx_parsers.py
demos/lx_population.py
demos/lx_simple.py
demos/lx_wallbase.py
demos/midnigh_comm.py
demos/weather.py
demos/browser_automation/moz_repl.py
demos/browser_automation/splinter_2.py
demos/browser_automation/splinter_demo.py
demos/browser_automation/splinter_headless.py
demos/browser_automation/splinter_project_euler.py
demos/browser_automation/splinter_wifi.py
demos/concurrency/gvnt.py
demos/concurrency/plain.py
demos/dictionary/dictionary.py
demos/dictionary/dictionary_2.py
demos/proxy/check.py
demos/webkit_etal/simple.py
demos/webkit_etal/spynner_0.py
jabbapylib/__init__.py
jabbapylib/config.py
jabbapylib.egg-info/PKG-INFO
jabbapylib.egg-info/SOURCES.txt
jabbapylib.egg-info/dependency_links.txt
jabbapylib.egg-info/requires.txt
jabbapylib.egg-info/top_level.txt
jabbapylib/apps/__init__.py
jabbapylib/apps/bing.py
jabbapylib/apps/define.py
jabbapylib/apps/fftabs.py
jabbapylib/apps/hacker_titles.py
jabbapylib/apps/imdb.py
jabbapylib/apps/is_net_back.py
jabbapylib/apps/ocr.py
jabbapylib/apps/pandora.py
jabbapylib/apps/proxies.py
jabbapylib/apps/say_google.py
jabbapylib/apps/set_wallpaper.py
jabbapylib/apps/slogan.py
jabbapylib/apps/trashmail.py
jabbapylib/apps/usernames.py
jabbapylib/apps/userpass.py
jabbapylib/browser/__init__.py
jabbapylib/browser/firefox.py
jabbapylib/clipboard/__init__.py
jabbapylib/clipboard/clipboard.py
jabbapylib/console/__init__.py
jabbapylib/console/autoflush.py
jabbapylib/console/color.py
jabbapylib/console/cursor.py
jabbapylib/dateandtime/__init__.py
jabbapylib/dateandtime/dateandtime.py
jabbapylib/dateandtime/timer.py
jabbapylib/decorators/__init__.py
jabbapylib/decorators/decorators.py
jabbapylib/dictionary/__init__.py
jabbapylib/dictionary/wordnik.py
jabbapylib/distance/__init__.py
jabbapylib/distance/dist.py
jabbapylib/filesystem/__init__.py
jabbapylib/filesystem/fs.py
jabbapylib/filesystem/ini.py
jabbapylib/hash/__init__.py
jabbapylib/hash/hash.py
jabbapylib/imgur/__init__.py
jabbapylib/imgur/imgur.py
jabbapylib/lib/BeautifulSoup.py
jabbapylib/lib/__init__.py
