Metadata-Version: 1.1
Name: jabbapylib
Version: 0.3.8
Summary: A lightweight, general-purpose Python library
Home-page: https://github.com/jabbalaci/jabbapylib
Author: Laszlo Szathmary
Author-email: jabba.laci@gmail.com
License: GPLv3
Keywords: jabba,library,scraper,api
Platform: Linux
Classifier: Development Status :: 4 - Beta
Classifier: Intended Audience :: Developers
Classifier: Natural Language :: English
Classifier: License :: OSI Approved :: GNU General Public License (GPL)
Classifier: Programming Language :: Python
Classifier: Programming Language :: Python :: 2
Classifier: Programming Language :: Python :: 2.7
Classifier: Operating System :: POSIX :: Linux
Classifier: Topic :: Utilities
